awslabs/__init__.py
awslabs/__main__.py
awslabs/awslabs.py
awslabs/betterguid.py
awslabs/challenge.py
awslabs/main.py
awslabs/track.py
awslabs/tracks/__init__.py
awslabs/tracks/apigateway/__init__.py
awslabs/tracks/apigateway/mytrack.py
awslabs/tracks/apigateway/challenges/01.py
awslabs/tracks/apigateway/challenges/__init__.py
awslabs/tracks/cloudformation/__init__.py
awslabs/tracks/cloudformation/mytrack.py
awslabs/tracks/cloudformation/challenges/01.py
awslabs/tracks/cloudformation/challenges/02.py
awslabs/tracks/cloudformation/challenges/03.py
awslabs/tracks/cloudformation/challenges/04.py
awslabs/tracks/cloudformation/challenges/05.py
awslabs/tracks/cloudformation/challenges/06.py
awslabs/tracks/cloudformation/challenges/__init__.py
awslabs/tracks/ecs/__init__.py
awslabs/tracks/ecs/docker_registry.py
awslabs/tracks/ecs/mytrack.py
awslabs/tracks/ecs/challenges/01.py
awslabs/tracks/ecs/challenges/02.py
awslabs/tracks/ecs/challenges/03.py
awslabs/tracks/ecs/challenges/04.py
awslabs/tracks/ecs/challenges/05.py
awslabs/tracks/ecs/challenges/06.py
awslabs/tracks/ecs/challenges/__init__.py
awslabs/tracks/ecs/challenges/create_service.py
awslabs/tracks/kinesis/__init__.py
awslabs/tracks/kinesis/mytrack.py
awslabs/tracks/kinesis/challenges/01.py
awslabs/tracks/kinesis/challenges/__init__.py
awslabs/tracks/s3/__init__.py
awslabs/tracks/s3/mytrack.py
awslabs/tracks/s3/challenges/01.py
awslabs/tracks/s3/challenges/02.py
awslabs/tracks/s3/challenges/__init__.py
awslabs/tracks/vpc/__init__.py
awslabs/tracks/vpc/mytrack.py
awslabs/tracks/vpc/challenges/01.py
awslabs/tracks/vpc/challenges/02.py
awslabs/tracks/vpc/challenges/03.py
awslabs/tracks/vpc/challenges/04.py
awslabs/tracks/vpc/challenges/05.py
awslabs/tracks/vpc/challenges/06.py
awslabs/tracks/vpc/challenges/07.py
awslabs/tracks/vpc/challenges/__init__.py
awslabs-0.1.0.dist-info/METADATA
awslabs-0.1.0.dist-info/RECORD
awslabs-0.1.0.dist-info/WHEEL
awslabs-0.1.0.dist-info/entry_points.txt
awslabs-0.1.0.dist-info/top_level.txt
